scpkit/__init__.py
scpkit/main.py
scpkit/src/__init__.py
scpkit/src/merge.py
scpkit/src/model.py
scpkit/src/util.py
scpkit/src/validate.py
scpkit/src/visualize.py
scpkit-1.0.0.dist-info/LICENSE
scpkit-1.0.0.dist-info/METADATA
scpkit-1.0.0.dist-info/WHEEL
scpkit-1.0.0.dist-info/entry_points.txt
scpkit-1.0.0.dist-info/top_level.txt
scpkit-1.0.0.dist-info/RECORD
