Metadata-Version: 2.1
Name: scpkit
Version: 1.0.0
Summary: This package helps consolidate service control policies in AWS
Home-page: https://www.aquia.us
Author: Aquia
Author-email: info@aquia.us
License: Apache License 2.0
Project-URL: Bug Tracker, https://github.com/aquia-inc/scpkit/issues
Project-URL: Source, https://github.com/aquia-inc/scpkit
License-File: LICENSE
Requires-Dist: boto3 >=1.28.66
Requires-Dist: docopt >=0.6.2
Requires-Dist: graphviz >=0.20.1
